AUTHORS
CHANGELOG.txt
DESCRIPTION
LICENSE
MANIFEST.in
README.rst
setup.cfg
setup.py
django_outlets.egg-info/PKG-INFO
django_outlets.egg-info/SOURCES.txt
django_outlets.egg-info/dependency_links.txt
django_outlets.egg-info/requires.txt
django_outlets.egg-info/top_level.txt
outlets/__init__.py
outlets/admin.py
outlets/models.py
outlets/urls.py
outlets/views.py
outlets/migrations/0001_initial.py
outlets/migrations/__init__.py
outlets/south_migrations/0001_initial.py
outlets/south_migrations/0002_auto__add_field_outlet_start_date__add_field_outlet_end_date__add_fiel.py
outlets/south_migrations/__init__.py
outlets/static/.empty
outlets/static/outlets/.empty
outlets/static/outlets/js/googlemap_outlets.js
outlets/templates/outlets/.empty
outlets/templates/outlets/outlet_list.html
outlets/templates/outlets/outlet_map_marker.html
outlets/templatetags/__init__.py
outlets/templatetags/outlets_tags.py
outlets/tests/__init__.py
outlets/tests/models_tests.py
outlets/tests/outlet_tags_tests.py
outlets/tests/settings.py
outlets/tests/test_settings.py
outlets/tests/urls.py
outlets/tests/views_tests.py