Metadata-Version: 1.0
Name: django-outlets
Version: 0.4.4
Summary: A reusable Django app that allows you to manage and display your stores
